{
  "name": "github-action-toolset",
  "displayName": "GitHub Action AI 工具集",
  "version": "1.0.0",
  "description": "GitHub Actions 构建和调试的 AI 规则工具集，帮助 AI 助手更好地完成 CI/CD 任务",
  "author": "firoyang",
  "license": "MIT",
  
  "keywords": [
    "github-actions",
    "ci-cd",
    "ai-rules",
    "workflow",
    "automation"
  ],
  
  "compatibility": {
    "project_types": [
      "nodejs",
      "python",
      "flutter",
      "rust",
      "go",
      "any"
    ],
    "platforms": [
      "windows",
      "macos",
      "linux"
    ]
  },
  
  "requirements": {
    "tools": [
      {
        "name": "gh",
        "version": ">=2.0.0",
        "required": true,
        "install_url": "https://cli.github.com/",
        "description": "GitHub CLI - 用于调试和触发工作流"
      }
    ]
  },
  
  "install": {
    "targets": {
      ".cursor/rules/github-actions/": {
        "source": "core/rules/",
        "files": ["*.mdc"],
        "merge": true,
        "overwrite": false,
        "description": "AI 行为规则文件"
      },
      "scripts/toolsets/github-actions/": {
        "source": "core/tools/go/dist/",
        "files": ["gh-action-debug-*"],
        "executable": true,
        "description": "Go 调试工具（自动检测平台并复制对应二进制文件）"
      }
    }
  },
  
  "features": [
    {
      "id": "ai-rules",
      "name": "AI 规则文件",
      "description": "教会 AI 助手如何构建和调试 GitHub Actions 的规则文件",
      "files": ["core/rules/*.mdc"],
      "essential": true
    },
    {
      "id": "debug-tools",
      "name": "Go 自动化调试工具",
      "description": "一键触发、监控和调试 GitHub Actions 工作流（Go 实现，高性能，跨平台）",
      "files": ["core/tools/go/cmd/gh-action-debug/main.go"],
      "essential": true
    }
  ],
  
  "scripts": {
    "validate": "bash core/tools/go/test-verify.sh"
  },
  
  "documentation": {
    "quickstart": "docs/guides/quickstart.md",
    "installation": "docs/INSTALL.md",
    "usage": "docs/USAGE.md",
    "scripts": "docs/SCRIPTS.md",
    "changelog": "CHANGELOG.md"
  },
  
  "repository": {
    "type": "git",
    "url": "https://github.com/shichao402/GithubActionAISelfBuilder.git"
  },
  
  "metadata": {
    "created": "2025-12-02",
    "updated": "2025-12-03",
    "toolset_version": "1.0.0",
    "schema_version": "1.0.0"
  }
}
